powerdict/__init__.py
powerdict/_nbdev.py
powerdict/cicd.py
powerdict/construct.py
powerdict/download.py
powerdict/pipeline.py
powerdict/update.py
powerdict-1.3.0.dist-info/LICENSE.txt
powerdict-1.3.0.dist-info/METADATA
powerdict-1.3.0.dist-info/WHEEL
powerdict-1.3.0.dist-info/top_level.txt
powerdict-1.3.0.dist-info/RECORD
