Metadata-Version: 2.1
Name: powerdict
Version: 1.3.0
Summary: A power station dictionary that enables mapping between various naming conventions and associated plant metadata
Home-page: https://github.com/OSUKED/Power-Station-Dictionary
Author: Ayrton Bourn
Author-email: ayrtonbourn@outlook.com
License: UNKNOWN
Platform: UNKNOWN
Classifier: Programming Language :: Python :: 3
Requires-Python: >=3.6
Requires-Dist: pandas (==1.1.5)
Requires-Dist: numpy (==1.19.4)
Requires-Dist: beautifulsoup4 (==4.9.3)
Requires-Dist: dagster (==0.9.21)
Requires-Dist: lxml (==4.6.2)
Requires-Dist: typer (==0.3.1)
